logedit/__init__.py
logedit/logedit.py
logedit/messages.json
logedit/system/changelog_writer.txt
logedit/system/commit_summarizer.txt
logedit-0.1.1.dist-info/METADATA
logedit-0.1.1.dist-info/WHEEL
logedit-0.1.1.dist-info/entry_points.txt
logedit-0.1.1.dist-info/top_level.txt
logedit-0.1.1.dist-info/RECORD
