Metadata-Version: 2.1
Name: logedit
Version: 0.1.1
Summary: A package to auto-generate changelogs from git commits using OpenAI's APIs
Home-page: https://github.com/gregpriday/logedit/
Author: Greg Priday
Author-email: greg@siteorigin.com
Classifier: Programming Language :: Python :: 3.7
Classifier: License :: OSI Approved :: MIT License
Requires-Dist: gitpython (>=3.1.14)
Requires-Dist: tqdm (>=4.60.0)
Requires-Dist: openai (>=0.27.0)
Requires-Dist: backoff (>=1.10.0)
Requires-Dist: tiktoken (>=0.4.0)
Requires-Dist: termcolor (>=2.3.0)
